[{"id":5543,"schoolId":8647,"schAttrId":1,"attrValue":"Chaminade College","schAttr":null,"school":null},{"id":5544,"schoolId":8647,"schAttrId":2,"attrValue":"490 Queen's Dr","schAttr":null,"school":null},{"id":5545,"schoolId":8647,"schAttrId":3,"attrValue":"Toronto","schAttr":null,"school":null},{"id":5546,"schoolId":8647,"schAttrId":4,"attrValue":"M6L 1M8","schAttr":null,"school":null},{"id":5547,"schoolId":8647,"schAttrId":5,"attrValue":"(416)\u00A0393-5509","schAttr":null,"school":null},{"id":5548,"schoolId":8647,"schAttrId":27,"attrValue":"","schAttr":null,"school":null},{"id":5549,"schoolId":8647,"schAttrId":28,"attrValue":"","schAttr":null,"school":null},{"id":5550,"schoolId":8647,"schAttrId":29,"attrValue":"9-12","schAttr":null,"school":null},{"id":5551,"schoolId":8647,"schAttrId":30,"attrValue":"0","schAttr":null,"school":null},{"id":5552,"schoolId":8647,"schAttrId":31,"attrValue":"1","schAttr":null,"school":null},{"id":5553,"schoolId":8647,"schAttrId":32,"attrValue":"0","schAttr":null,"school":null},{"id":5554,"schoolId":8647,"schAttrId":33,"attrValue":"0","schAttr":null,"school":null},{"id":5555,"schoolId":8647,"schAttrId":34,"attrValue":"0","schAttr":null,"school":null},{"id":5556,"schoolId":8647,"schAttrId":35,"attrValue":"0","schAttr":null,"school":null},{"id":5557,"schoolId":8647,"schAttrId":36,"attrValue":"0","schAttr":null,"school":null},{"id":5558,"schoolId":8647,"schAttrId":37,"attrValue":"","schAttr":null,"school":null},{"id":5559,"schoolId":8647,"schAttrId":38,"attrValue":"","schAttr":null,"school":null},{"id":5560,"schoolId":8647,"schAttrId":39,"attrValue":"John Shanahan","schAttr":null,"school":null},{"id":5561,"schoolId":8647,"schAttrId":40,"attrValue":"john.shanahan@tcdsb.org","schAttr":null,"school":null},{"id":5563,"schoolId":8647,"schAttrId":42,"attrValue":"sal.piccininni@tcdsb.org","schAttr":null,"school":null},{"id":5564,"schoolId":8647,"schAttrId":43,"attrValue":"","schAttr":null,"school":null},{"id":5565,"schoolId":8647,"schAttrId":44,"attrValue":"946","schAttr":null,"school":null},{"id":5566,"schoolId":8647,"schAttrId":45,"attrValue":"0","schAttr":null,"school":null},{"id":5567,"schoolId":8647,"schAttrId":46,"attrValue":"0","schAttr":null,"school":null},{"id":5568,"schoolId":8647,"schAttrId":47,"attrValue":"","schAttr":null,"school":null},{"id":5569,"schoolId":8647,"schAttrId":48,"attrValue":"1","schAttr":null,"school":null},{"id":5570,"schoolId":8647,"schAttrId":49,"attrValue":"102800765","schAttr":null,"school":null},{"id":5571,"schoolId":8647,"schAttrId":50,"attrValue":"METROPOLITAN SEPARATE SCHOOL BOARD; TORONTO CATHOLIC DISTRICT SCHOOL BOARD","schAttr":null,"school":null},{"id":5572,"schoolId":8647,"schAttrId":51,"attrValue":"","schAttr":null,"school":null},{"id":5573,"schoolId":8647,"schAttrId":52,"attrValue":"Open","schAttr":null,"school":null},{"id":5574,"schoolId":8647,"schAttrId":53,"attrValue":"","schAttr":null,"school":null},{"id":5575,"schoolId":8647,"schAttrId":54,"attrValue":"","schAttr":null,"school":null},{"id":5576,"schoolId":8647,"schAttrId":55,"attrValue":"1","schAttr":null,"school":null},{"id":29128,"schoolId":8647,"schAttrId":57,"attrValue":"{\"Center\":{\"Y\":5420675.0686567388,\"X\":-8849447.73622068},\"Height\":254.84959310479462,\"Width\":486.98981652781367,\"Right\":-8849204.2413124163,\"Bottom\":5420547.6438601864,\"Left\":-8849691.2311289441,\"Top\":5420802.4934532912}","schAttr":null,"school":null},{"id":102133,"schoolId":8647,"schAttrId":58,"attrValue":"http://www.edu.gov.on.ca/eng/sift/schoolProfileSec.asp?SCH_NUMBER=695947","schAttr":null,"school":null},{"id":198156,"schoolId":8647,"schAttrId":41,"attrValue":"CAT_ENG_SEC","schAttr":null,"school":null},{"id":611918,"schoolId":8647,"schAttrId":65,"attrValue":"","schAttr":null,"school":null},{"id":613483,"schoolId":8647,"schAttrId":67,"attrValue":"xZi9B4340NhUbSiaRGaGGQ==","schAttr":null,"school":null},{"id":613484,"schoolId":8647,"schAttrId":68,"attrValue":"SlN6t9XrXmBYf9JGmpZVKg==","schAttr":null,"school":null},{"id":643643,"schoolId":8647,"schAttrId":69,"attrValue":"102800765","schAttr":null,"school":null},{"id":650447,"schoolId":8647,"schAttrId":70,"attrValue":"CAT_ENG_SEC","schAttr":null,"school":null},{"id":664106,"schoolId":8647,"schAttrId":72,"attrValue":"1","schAttr":null,"school":null},{"id":776139,"schoolId":8647,"schAttrId":56,"attrValue":"0","schAttr":null,"school":null},{"id":776140,"schoolId":8647,"schAttrId":59,"attrValue":"","schAttr":null,"school":null},{"id":776141,"schoolId":8647,"schAttrId":60,"attrValue":"","schAttr":null,"school":null},{"id":776142,"schoolId":8647,"schAttrId":61,"attrValue":"2017-10-25 07:12:52","schAttr":null,"school":null},{"id":776143,"schoolId":8647,"schAttrId":71,"attrValue":"","schAttr":null,"school":null}]