[{"id":5679,"schoolId":8651,"schAttrId":1,"attrValue":"Don Bosco CSS","schAttr":null,"school":null},{"id":5680,"schoolId":8651,"schAttrId":2,"attrValue":"2 St Andrew's Blvd","schAttr":null,"school":null},{"id":5681,"schoolId":8651,"schAttrId":3,"attrValue":"Weston","schAttr":null,"school":null},{"id":5682,"schoolId":8651,"schAttrId":4,"attrValue":"M9R 1V8","schAttr":null,"school":null},{"id":5683,"schoolId":8651,"schAttrId":5,"attrValue":"(416)\u00A0393-5525","schAttr":null,"school":null},{"id":5684,"schoolId":8651,"schAttrId":27,"attrValue":"","schAttr":null,"school":null},{"id":5685,"schoolId":8651,"schAttrId":28,"attrValue":"","schAttr":null,"school":null},{"id":5686,"schoolId":8651,"schAttrId":29,"attrValue":"9-12","schAttr":null,"school":null},{"id":5687,"schoolId":8651,"schAttrId":30,"attrValue":"0","schAttr":null,"school":null},{"id":5688,"schoolId":8651,"schAttrId":31,"attrValue":"1","schAttr":null,"school":null},{"id":5689,"schoolId":8651,"schAttrId":32,"attrValue":"0","schAttr":null,"school":null},{"id":5690,"schoolId":8651,"schAttrId":33,"attrValue":"0","schAttr":null,"school":null},{"id":5691,"schoolId":8651,"schAttrId":34,"attrValue":"0","schAttr":null,"school":null},{"id":5692,"schoolId":8651,"schAttrId":35,"attrValue":"0","schAttr":null,"school":null},{"id":5693,"schoolId":8651,"schAttrId":36,"attrValue":"0","schAttr":null,"school":null},{"id":5694,"schoolId":8651,"schAttrId":37,"attrValue":"Michael Rossetti","schAttr":null,"school":null},{"id":5695,"schoolId":8651,"schAttrId":38,"attrValue":"","schAttr":null,"school":null},{"id":5696,"schoolId":8651,"schAttrId":39,"attrValue":"John Shanahan","schAttr":null,"school":null},{"id":5697,"schoolId":8651,"schAttrId":40,"attrValue":"john.shanahan@tcdsb.org","schAttr":null,"school":null},{"id":5699,"schoolId":8651,"schAttrId":42,"attrValue":"joseph.martino@tcdsb.org","schAttr":null,"school":null},{"id":5700,"schoolId":8651,"schAttrId":43,"attrValue":"","schAttr":null,"school":null},{"id":5701,"schoolId":8651,"schAttrId":44,"attrValue":"709","schAttr":null,"school":null},{"id":5702,"schoolId":8651,"schAttrId":45,"attrValue":"0","schAttr":null,"school":null},{"id":5703,"schoolId":8651,"schAttrId":46,"attrValue":"0","schAttr":null,"school":null},{"id":5704,"schoolId":8651,"schAttrId":47,"attrValue":"","schAttr":null,"school":null},{"id":5705,"schoolId":8651,"schAttrId":48,"attrValue":"0","schAttr":null,"school":null},{"id":5706,"schoolId":8651,"schAttrId":49,"attrValue":"73930177","schAttr":null,"school":null},{"id":5707,"schoolId":8651,"schAttrId":50,"attrValue":"METROPOLITAN SEPARATE SCHOOL BOARD; TORONTO CATHOLIC DISTRICT SCHOOL BOARD","schAttr":null,"school":null},{"id":5708,"schoolId":8651,"schAttrId":51,"attrValue":"","schAttr":null,"school":null},{"id":5709,"schoolId":8651,"schAttrId":52,"attrValue":"Closed","schAttr":null,"school":null},{"id":5710,"schoolId":8651,"schAttrId":53,"attrValue":"","schAttr":null,"school":null},{"id":5711,"schoolId":8651,"schAttrId":54,"attrValue":"","schAttr":null,"school":null},{"id":5712,"schoolId":8651,"schAttrId":55,"attrValue":"0","schAttr":null,"school":null},{"id":29132,"schoolId":8651,"schAttrId":57,"attrValue":"{\"Center\":{\"Y\":5419426.5579867605,\"X\":-8855497.512320295},\"Height\":509.69918620865792,\"Width\":973.979633051902,\"Right\":-8855010.522503769,\"Bottom\":5419171.7083936566,\"Left\":-8855984.50213682,\"Top\":5419681.4075798653}","schAttr":null,"school":null},{"id":104969,"schoolId":8651,"schAttrId":58,"attrValue":"http://www.edu.gov.on.ca/eng/sift/schoolProfileSec.asp?SCH_NUMBER=703184","schAttr":null,"school":null},{"id":198160,"schoolId":8651,"schAttrId":41,"attrValue":"CAT_ENG_SEC","schAttr":null,"school":null},{"id":611922,"schoolId":8651,"schAttrId":65,"attrValue":"","schAttr":null,"school":null},{"id":613491,"schoolId":8651,"schAttrId":67,"attrValue":"vgRrV0rfZVUrF+hfbZYO2A==","schAttr":null,"school":null},{"id":613492,"schoolId":8651,"schAttrId":68,"attrValue":"+E9OiMUSVsAMAwB+uBYbtA==","schAttr":null,"school":null},{"id":643647,"schoolId":8651,"schAttrId":69,"attrValue":"73930177","schAttr":null,"school":null},{"id":650451,"schoolId":8651,"schAttrId":70,"attrValue":"CAT_ENG_SEC","schAttr":null,"school":null},{"id":664110,"schoolId":8651,"schAttrId":72,"attrValue":"1","schAttr":null,"school":null},{"id":788862,"schoolId":8651,"schAttrId":56,"attrValue":"1","schAttr":null,"school":null},{"id":788863,"schoolId":8651,"schAttrId":59,"attrValue":"","schAttr":null,"school":null},{"id":788864,"schoolId":8651,"schAttrId":60,"attrValue":"","schAttr":null,"school":null},{"id":788865,"schoolId":8651,"schAttrId":61,"attrValue":"2020-08-25 06:08:27","schAttr":null,"school":null},{"id":788866,"schoolId":8651,"schAttrId":71,"attrValue":"","schAttr":null,"school":null},{"id":872834,"schoolId":8651,"schAttrId":73,"attrValue":"","schAttr":null,"school":null},{"id":872835,"schoolId":8651,"schAttrId":74,"attrValue":"","schAttr":null,"school":null},{"id":872836,"schoolId":8651,"schAttrId":75,"attrValue":"","schAttr":null,"school":null}]